PyAutoscoper/__init__.py
PyAutoscoper/connect.py
PyAutoscoper-2.0.0.dist-info/METADATA
PyAutoscoper-2.0.0.dist-info/WHEEL
PyAutoscoper-2.0.0.dist-info/top_level.txt
PyAutoscoper-2.0.0.dist-info/RECORD
