Metadata-Version: 2.1
Name: PyAutoscoper
Version: 2.0.0
Summary: A Python client library for the Autoscoper API
Author-email: "Anthony J. Lombardi" <anthony.lombardi@kitware.com>
License: Autoscoper License
Project-URL: homepage, https://autoscoperm.slicer.org/
Project-URL: repository, https://github.com/BrownBiomechanics/Autoscoper/tree/main/scripts/python
Requires-Python: >=3.6
Provides-Extra: dev
Requires-Dist: black (>=22.3.0) ; extra == 'dev'
